{
  "name": "Scrape",
  "nodes": [
    {
      "parameters": {
        "method": "POST",
        "url": "https://production-sfo.browserless.io/chrome/bql",
        "authentication": "genericCredentialType",
        "genericAuthType": "httpQueryAuth",
        "sendBody": true,
        "bodyParameters": {
          "parameters": [
            {
              "name": "query",
              "value": "=mutation GrabTOCAndHTMLWithURL {\n  goto(url: \"{{ $('Set Inputs').item.json.Source }}\", waitUntil: networkIdle) {\n    status\n    url\n  }\n\n  pause: waitForTimeout(time: 1500) {\n    time\n  }\n\n  # Capture the main HTML document response + headers\n  documentResponse: response(type: [document], wait: false) {\n    url\n    status\n    headers {\n      name\n      value\n    }\n  }\n\n  # Capture JavaScript responses + headers\n  scripts: response(type: [script], wait: false) {\n    url\n    headers {\n      name\n      value\n    }\n    body\n  }\n\n  finalUrl: url {\n    url\n  }\n\n  fullHtml: html {\n    html\n  }\n}"
            }
          ]
        },
        "options": {
          "timeout": 120000
        }
      },
      "type": "n8n-nodes-base.httpRequest",
      "typeVersion": 4.2,
      "position": [
        0,
        288
      ],
      "id": "216496e8-3c7b-437e-85cb-f3eac07e0c6b",
      "name": "Browserless",
      "retryOnFail": true,
      "maxTries": 2,
      "waitBetweenTries": 5000,
      "disabled": true,
      "onError": "continueErrorOutput"
    },
    {
      "parameters": {
        "rules": {
          "values": [
            {
              "conditions": {
                "options": {
                  "caseSensitive": true,
                  "leftValue": "",
                  "typeValidation": "strict",
                  "version": 2
                },
                "conditions": [
                  {
                    "id": "cca9a8b7-a815-4f13-908c-79a5c3d99b21",
                    "leftValue": "={{ $json.Source }}",
                    "rightValue": "=^https?:\\/\\/(?!.*\\.(pdf|PDF|Pdf)(\\?|$))[^\\s\\/$.?#].[^\\s]*$",
                    "operator": {
                      "type": "string",
                      "operation": "regex"
                    }
                  }
                ],
                "combinator": "and"
              },
              "renameOutput": true,
              "outputKey": "HTML"
            },
            {
              "conditions": {
                "options": {
                  "caseSensitive": true,
                  "leftValue": "",
                  "typeValidation": "strict",
                  "version": 2
                },
                "conditions": [
                  {
                    "leftValue": "={{ $json.Source }}",
                    "rightValue": ".pdf",
                    "operator": {
                      "type": "string",
                      "operation": "contains"
                    },
                    "id": "8c326d29-c843-4ca7-af58-06df08ddfece"
                  }
                ],
                "combinator": "and"
              },
              "renameOutput": true,
              "outputKey": "PDF"
            }
          ]
        },
        "options": {
          "fallbackOutput": "extra"
        }
      },
      "type": "n8n-nodes-base.switch",
      "typeVersion": 3.2,
      "position": [
        -1120,
        736
      ],
      "id": "6e897c5b-2d0d-4ebb-8cab-c7f1fb208895",
      "name": "Type Switch"
    },
    {
      "parameters": {
        "inputSource": "passthrough"
      },
      "type": "n8n-nodes-base.executeWorkflowTrigger",
      "typeVersion": 1.1,
      "position": [
        -1568,
        848
      ],
      "id": "2c79f2ed-053a-4a77-a813-f34df4bec3e5",
      "name": "When Executed by Another Workflow"
    },
    {
      "parameters": {},
      "type": "n8n-nodes-base.manualTrigger",
      "typeVersion": 1,
      "position": [
        -1792,
        656
      ],
      "id": "2938ee34-6109-4967-b1de-2da177c275e8",
      "name": "When clicking ‘Execute workflow’"
    },
    {
      "parameters": {
        "errorMessage": "Check Fallback"
      },
      "type": "n8n-nodes-base.stopAndError",
      "typeVersion": 1,
      "position": [
        -896,
        944
      ],
      "id": "a2a529b2-0059-4cb9-ad98-fcaa3a6b8de7",
      "name": "Stop and Error"
    },
    {
      "parameters": {
        "url": "={{ $('Set Inputs').item.json.Source }}",
        "sendHeaders": true,
        "headerParameters": {
          "parameters": [
            {
              "name": "User-Agent",
              "value": "Mozilla/5.0 (Windows NT 10.0; Win64; x64) AppleWebKit/537.36 (KHTML, like Gecko) Chrome/133.0.0.0 Safari/537.36"
            },
            {
              "name": "Referer",
              "value": "={{ $('Set Inputs').item.json.Source.split('/').slice(0,3).join('/') + '/' }}"
            }
          ]
        },
        "options": {
          "redirect": {
            "redirect": {}
          },
          "response": {
            "response": {
              "fullResponse": true,
              "responseFormat": "text"
            }
          },
          "timeout": 120000
        }
      },
      "id": "70bb3a66-73d6-4072-bc96-0464bd48b57e",
      "name": "HTTP Request",
      "type": "n8n-nodes-base.httpRequest",
      "position": [
        -224,
        96
      ],
      "typeVersion": 4.2,
      "executeOnce": false,
      "retryOnFail": true,
      "maxTries": 2,
      "waitBetweenTries": 5000,
      "onError": "continueErrorOutput"
    },
    {
      "parameters": {
        "operation": "append",
        "documentId": {
          "__rl": true,
          "value": "={{ $vars.manager_doc }}",
          "mode": "id"
        },
        "sheetName": {
          "__rl": true,
          "value": "={{ $vars.manager_sheet_error }}",
          "mode": "id"
        },
        "columns": {
          "mappingMode": "defineBelow",
          "value": {
            "Source": "={{ $('Set Inputs').all()[0].json.Source }}",
            "Job": "={{ $('Set Inputs').all()[0].json.Job }}",
            "Execution": "={{ $('Set Inputs').all()[0].json.Execution }}",
            "Error": "=HTTP Request - {{ $json.error.status ?? $json.message }}",
            "Datetime": "={{ $now.toFormat(\"yyyy-MM-dd HH:mm:ss\") }}"
          },
          "matchingColumns": [
            "Source"
          ],
          "schema": [
            {
              "id": "Source",
              "displayName": "Source",
              "required": false,
              "defaultMatch": false,
              "display": true,
              "type": "string",
              "canBeUsedToMatch": true,
              "removed": false
            },
            {
              "id": "Datetime",
              "displayName": "Datetime",
              "required": false,
              "defaultMatch": false,
              "display": true,
              "type": "string",
              "canBeUsedToMatch": true,
              "removed": false
            },
            {
              "id": "Error",
              "displayName": "Error",
              "required": false,
              "defaultMatch": false,
              "display": true,
              "type": "string",
              "canBeUsedToMatch": true,
              "removed": false
            },
            {
              "id": "Job",
              "displayName": "Job",
              "required": false,
              "defaultMatch": false,
              "display": true,
              "type": "string",
              "canBeUsedToMatch": true
            },
            {
              "id": "Execution",
              "displayName": "Execution",
              "required": false,
              "defaultMatch": false,
              "display": true,
              "type": "string",
              "canBeUsedToMatch": true
            }
          ],
          "attemptToConvertTypes": false,
          "convertFieldsToString": false
        },
        "options": {}
      },
      "type": "n8n-nodes-base.googleSheets",
      "typeVersion": 4.7,
      "position": [
        0,
        0
      ],
      "id": "f9289281-fe6e-4377-b23a-00eec63bd0b0",
      "name": "Append Error (HTTP Request)",
      "retryOnFail": true,
      "maxTries": 2,
      "waitBetweenTries": 5000
    },
    {
      "parameters": {
        "operation": "append",
        "documentId": {
          "__rl": true,
          "value": "={{ $vars.manager_doc }}",
          "mode": "id"
        },
        "sheetName": {
          "__rl": true,
          "value": "={{ $vars.manager_sheet_error }}",
          "mode": "id"
        },
        "columns": {
          "mappingMode": "defineBelow",
          "value": {
            "Source": "={{ $('Set Inputs').all()[0].json.Source }}",
            "Job": "={{ $('Set Inputs').all()[0].json.Job }}",
            "Execution": "={{ $('Set Inputs').all()[0].json.Execution }}",
            "Error": "=Browserless - {{ $json.error.status ?? $json.message }}",
            "Datetime": "={{ $now.toFormat(\"yyyy-MM-dd HH:mm:ss\") }}"
          },
          "matchingColumns": [
            "Source"
          ],
          "schema": [
            {
              "id": "Source",
              "displayName": "Source",
              "required": false,
              "defaultMatch": false,
              "display": true,
              "type": "string",
              "canBeUsedToMatch": true,
              "removed": false
            },
            {
              "id": "Datetime",
              "displayName": "Datetime",
              "required": false,
              "defaultMatch": false,
              "display": true,
              "type": "string",
              "canBeUsedToMatch": true,
              "removed": false
            },
            {
              "id": "Error",
              "displayName": "Error",
              "required": false,
              "defaultMatch": false,
              "display": true,
              "type": "string",
              "canBeUsedToMatch": true,
              "removed": false
            },
            {
              "id": "Job",
              "displayName": "Job",
              "required": false,
              "defaultMatch": false,
              "display": true,
              "type": "string",
              "canBeUsedToMatch": true
            },
            {
              "id": "Execution",
              "displayName": "Execution",
              "required": false,
              "defaultMatch": false,
              "display": true,
              "type": "string",
              "canBeUsedToMatch": true
            }
          ],
          "attemptToConvertTypes": false,
          "convertFieldsToString": false
        },
        "options": {}
      },
      "type": "n8n-nodes-base.googleSheets",
      "typeVersion": 4.7,
      "position": [
        224,
        192
      ],
      "id": "476624aa-80f1-4268-8246-1840464d6940",
      "name": "Append Error (Browserless)",
      "retryOnFail": true,
      "maxTries": 2,
      "waitBetweenTries": 5000
    },
    {
      "parameters": {
        "assignments": {
          "assignments": [
            {
              "id": "27b599da-f9af-4259-8a3b-2fb77af04eac",
              "name": "Source",
              "value": "={{\n  (() => {\n    const html = ($json?.data ?? '').toString?.() ?? '';\n\n    const canonical =\n      html.match(/<link[^>]*rel=[\"']canonical[\"'][^>]*href=[\"']([^\"']+)[\"']/i)?.[1] ?? '';\n\n    const finalUrl =\n      $json?.data?.finalUrl?.url ?? $json?.finalUrl?.url ?? '';\n\n    const source =\n      $('Set Inputs').all?.()?.[0]?.json?.Source ?? '';\n\n    const clean = (v) => String(v ?? '').replace(/[\\u0000-\\u001F\\u007F]/g, '').trim();\n\n    const untouched = clean(finalUrl) || clean(source) || '';\n    const canon = clean(canonical);\n\n    const host = (u) => (String(u).match(/^https?:\\/\\/([^\\/?#]+)/i)?.[1] ?? '').toLowerCase();\n\n    return (canon && untouched && host(canon) && host(untouched) && host(canon) !== host(untouched))\n      ? canon\n      : untouched;\n  })()\n}}",
              "type": "string"
            },
            {
              "id": "86f0f2b7-7b34-4821-bf08-3d817fc327d3",
              "name": "body",
              "value": "={{ $json?.data?.fullHtml?.html ?? $json?.data ?? '' }}",
              "type": "string"
            },
            {
              "id": "d51d17ea-010d-4c55-8bf0-1a3418fc0b34",
              "name": "title",
              "value": "={{\n  (\n    $json?.data?.fullHtml?.html\n      ?.match?.(/<title>(.*?)<\\/title>/i)\n      ?.[1]\n    ?? $json?.data\n      ?.match?.(/<title>(.*?)<\\/title>/i)\n      ?.[1]\n    ?? ''\n  )\n}}",
              "type": "string"
            },
            {
              "id": "fbfc015a-c354-4688-abf3-013b9ee8eb46",
              "name": "last-modified",
              "value": "={{\n  $json?.data?.scripts?.[0]?.headers?.find?.(\n    h => (h?.name ?? '').toLowerCase() === 'last-modified'\n  )?.value\n  ?? $json?.headers?.['last-modified']\n  ?? $json?.headers?.['Last-Modified']\n}}",
              "type": "string"
            },
            {
              "id": "9401651c-e78a-41d1-99a3-7f3c74322da9",
              "name": "etag",
              "value": "={{\n  (\n    $json?.data?.scripts?.[0]?.headers?.find?.(\n      h => (h?.name ?? '').toLowerCase() === 'etag'\n    )?.value\n    ?? $json?.headers?.etag\n    ?? $json?.headers?.['etag']\n    ?? $json?.headers?.['ETag']\n  )?.replace(/\"/g, '')\n}}",
              "type": "string"
            },
            {
              "id": "6a2f3c37-86e1-4fc6-b300-582e9bb1999a",
              "name": "scripts",
              "value": "={{ $json?.data?.scripts ?? [] }}",
              "type": "array"
            }
          ]
        },
        "options": {}
      },
      "type": "n8n-nodes-base.set",
      "typeVersion": 3.4,
      "position": [
        224,
        384
      ],
      "id": "ed7630b2-13af-46f7-9c12-11181b42a11d",
      "name": "Set Source"
    },
    {
      "parameters": {
        "assignments": {
          "assignments": [
            {
              "id": "c835e763-1639-489c-83c6-134bc954e486",
              "name": "Source",
              "value": "https://www.ready.gov/",
              "type": "string"
            },
            {
              "id": "2435aec3-f6fd-459d-8294-68e1f0a2158d",
              "name": "Job",
              "value": "1001",
              "type": "string"
            }
          ]
        },
        "options": {}
      },
      "type": "n8n-nodes-base.set",
      "typeVersion": 3.4,
      "position": [
        -1568,
        656
      ],
      "id": "36892ebf-5b32-41d8-9d0e-04a5005a5b0a",
      "name": "Manual"
    },
    {
      "parameters": {
        "assignments": {
          "assignments": [
            {
              "id": "7c65d6d7-1b45-4ec1-aede-461101a9afe6",
              "name": "Source",
              "value": "={{ $json.Source }}",
              "type": "string"
            },
            {
              "id": "a13a4dad-b477-41b8-a066-2963e42de13d",
              "name": "Job",
              "value": "={{ $json.Job }}",
              "type": "string"
            },
            {
              "id": "ff496dbd-bf79-4ef7-a811-a80b1a3890fd",
              "name": "Execution",
              "value": "=Scrape-{{$execution.id}}",
              "type": "string"
            }
          ]
        },
        "options": {}
      },
      "type": "n8n-nodes-base.set",
      "typeVersion": 3.4,
      "position": [
        -1344,
        752
      ],
      "id": "2345582f-3fbc-4679-a1fc-4c382c5d72f7",
      "name": "Set Inputs"
    },
    {
      "parameters": {
        "conditions": {
          "options": {
            "caseSensitive": true,
            "leftValue": "",
            "typeValidation": "strict",
            "version": 2
          },
          "conditions": [
            {
              "id": "31069597-4422-40c5-987b-3f50fafe2fa1",
              "leftValue": "={{ $json.headers['content-type'] }}",
              "rightValue": "html",
              "operator": {
                "type": "string",
                "operation": "contains"
              }
            }
          ],
          "combinator": "and"
        },
        "options": {}
      },
      "type": "n8n-nodes-base.if",
      "typeVersion": 2.2,
      "position": [
        -640,
        496
      ],
      "id": "90ea971d-1b35-4534-9e01-f511be0b683a",
      "name": "HTML Catch"
    },
    {
      "parameters": {
        "assignments": {
          "assignments": [
            {
              "id": "450a4e34-4915-44b5-8308-a754d3ec15a7",
              "name": "Source",
              "value": "={{ $json.Source }}",
              "type": "string"
            }
          ]
        },
        "options": {}
      },
      "type": "n8n-nodes-base.set",
      "typeVersion": 3.4,
      "position": [
        -400,
        256
      ],
      "id": "2c95afae-e460-4f9b-9b2d-a25344c90e0a",
      "name": "HTML Failover"
    },
    {
      "parameters": {
        "operation": "append",
        "documentId": {
          "__rl": true,
          "value": "={{ $vars.manager_doc }}",
          "mode": "id"
        },
        "sheetName": {
          "__rl": true,
          "value": "={{ $vars.manager_sheet_error }}",
          "mode": "id"
        },
        "columns": {
          "mappingMode": "defineBelow",
          "value": {
            "Source": "={{ $('Set Inputs').all()[0].json.Source }}",
            "Job": "={{ $('Set Inputs').all()[0].json.Job }}",
            "Execution": "={{ $('Set Inputs').all()[0].json.Execution }}",
            "Error": "=PDF - {{ $json.error.status ?? $json.message }}",
            "Datetime": "={{ $now.toFormat(\"yyyy-MM-dd HH:mm:ss\") }}"
          },
          "matchingColumns": [
            "Source"
          ],
          "schema": [
            {
              "id": "Source",
              "displayName": "Source",
              "required": false,
              "defaultMatch": false,
              "display": true,
              "type": "string",
              "canBeUsedToMatch": true,
              "removed": false
            },
            {
              "id": "Datetime",
              "displayName": "Datetime",
              "required": false,
              "defaultMatch": false,
              "display": true,
              "type": "string",
              "canBeUsedToMatch": true,
              "removed": false
            },
            {
              "id": "Error",
              "displayName": "Error",
              "required": false,
              "defaultMatch": false,
              "display": true,
              "type": "string",
              "canBeUsedToMatch": true,
              "removed": false
            },
            {
              "id": "Job",
              "displayName": "Job",
              "required": false,
              "defaultMatch": false,
              "display": true,
              "type": "string",
              "canBeUsedToMatch": true
            },
            {
              "id": "Execution",
              "displayName": "Execution",
              "required": false,
              "defaultMatch": false,
              "display": true,
              "type": "string",
              "canBeUsedToMatch": true
            }
          ],
          "attemptToConvertTypes": false,
          "convertFieldsToString": false
        },
        "options": {}
      },
      "type": "n8n-nodes-base.googleSheets",
      "typeVersion": 4.7,
      "position": [
        -672,
        1056
      ],
      "id": "2c325b79-5216-476f-a8ef-62c61afcef22",
      "name": "Append Error (PDF)",
      "retryOnFail": true,
      "maxTries": 2,
      "waitBetweenTries": 5000
    },
    {
      "parameters": {
        "operation": "append",
        "documentId": {
          "__rl": true,
          "value": "={{ $vars.crawl_doc }}",
          "mode": "id"
        },
        "sheetName": {
          "__rl": true,
          "value": "={{ $vars.crawl_sheet_output }}",
          "mode": "id"
        },
        "columns": {
          "mappingMode": "defineBelow",
          "value": {
            "Source": "={{ $('Set Inputs').all()[0].json.Source }}",
            "Job": "={{ $('Set Inputs').all()[0].json.Job }}",
            "Execution": "={{ $('Set Inputs').all()[0].json.Execution }}",
            "Datetime": "={{ $now.toFormat(\"yyyy-MM-dd HH:mm:ss\") }}"
          },
          "matchingColumns": [
            "Source"
          ],
          "schema": [
            {
              "id": "Source",
              "displayName": "Source",
              "required": false,
              "defaultMatch": false,
              "display": true,
              "type": "string",
              "canBeUsedToMatch": true,
              "removed": false
            },
            {
              "id": "Datetime",
              "displayName": "Datetime",
              "required": false,
              "defaultMatch": false,
              "display": true,
              "type": "string",
              "canBeUsedToMatch": true,
              "removed": false
            },
            {
              "id": "Job",
              "displayName": "Job",
              "required": false,
              "defaultMatch": false,
              "display": true,
              "type": "string",
              "canBeUsedToMatch": true,
              "removed": false
            },
            {
              "id": "Execution",
              "displayName": "Execution",
              "required": false,
              "defaultMatch": false,
              "display": true,
              "type": "string",
              "canBeUsedToMatch": true,
              "removed": false
            }
          ],
          "attemptToConvertTypes": false,
          "convertFieldsToString": false
        },
        "options": {}
      },
      "type": "n8n-nodes-base.googleSheets",
      "typeVersion": 4.7,
      "position": [
        -448,
        464
      ],
      "id": "246e93c3-4ccd-4955-88bc-526276108261",
      "name": "Append Crawl-Output (PDF)",
      "retryOnFail": true,
      "maxTries": 2,
      "waitBetweenTries": 5000
    },
    {
      "parameters": {
        "assignments": {
          "assignments": []
        },
        "options": {}
      },
      "type": "n8n-nodes-base.set",
      "typeVersion": 3.4,
      "position": [
        -224,
        464
      ],
      "id": "53e0c37d-ceab-46f5-96a3-5b78d0a9e56f",
      "name": "Set Workflow Output (PDF)",
      "executeOnce": true
    },
    {
      "parameters": {
        "url": "={{ $('Set Inputs').item.json.Source }}",
        "sendHeaders": true,
        "headerParameters": {
          "parameters": [
            {
              "name": "User-Agent",
              "value": "Mozilla/5.0 (Windows NT 10.0; Win64; x64) AppleWebKit/537.36 (KHTML, like Gecko) Chrome/133.0.0.0 Safari/537.36"
            },
            {
              "name": "Referer",
              "value": "={{ $('Set Inputs').item.json.Source.split('/').slice(0,3).join('/') + '/' }}"
            }
          ]
        },
        "options": {
          "redirect": {
            "redirect": {}
          },
          "response": {
            "response": {
              "fullResponse": true,
              "responseFormat": "file"
            }
          },
          "timeout": 120000
        }
      },
      "type": "n8n-nodes-base.httpRequest",
      "typeVersion": 4.2,
      "position": [
        -896,
        752
      ],
      "id": "bb790e9b-c731-4b97-84e8-164f26dcbb42",
      "name": "PDF Binary",
      "retryOnFail": true,
      "maxTries": 2,
      "waitBetweenTries": 5000,
      "onError": "continueErrorOutput"
    },
    {
      "parameters": {
        "content": "\n\n\n\n\n\n\n\n\n\n\n\n\n\nCreate Generic Credential\nType: Query Auth\nName: token\nYour Browserless API Key",
        "height": 272,
        "color": 7
      },
      "type": "n8n-nodes-base.stickyNote",
      "typeVersion": 1,
      "position": [
        -64,
        288
      ],
      "id": "65ad468f-994c-428b-9aec-09e87edef735",
      "name": "Sticky Note1"
    },
    {
      "parameters": {
        "errorMessage": "=Check HTTP Request: {{ $json.Error }}"
      },
      "type": "n8n-nodes-base.stopAndError",
      "typeVersion": 1,
      "position": [
        224,
        0
      ],
      "id": "bed99adf-1e04-4eb6-97c5-001c5b02a1da",
      "name": "Stop and Error (HTTP Request)",
      "disabled": true
    },
    {
      "parameters": {
        "errorMessage": "=Check Browserless: {{ $json.Error }}"
      },
      "type": "n8n-nodes-base.stopAndError",
      "typeVersion": 1,
      "position": [
        448,
        192
      ],
      "id": "66e83d0d-9473-45bd-9ad0-26075a53053a",
      "name": "Stop and Error (Browserless)",
      "disabled": true
    },
    {
      "parameters": {
        "errorMessage": "=Check PDF: {{ $json.Error }}"
      },
      "type": "n8n-nodes-base.stopAndError",
      "typeVersion": 1,
      "position": [
        -448,
        1056
      ],
      "id": "9cfdaa26-da8d-4a82-bb44-d7772bbdf10e",
      "name": "Stop and Error (PDF)",
      "disabled": true
    },
    {
      "parameters": {
        "content": "## Scrape\nScrapes a given URL and saves the HTML or PDF content.\n",
        "height": 80,
        "width": 752,
        "color": 4
      },
      "type": "n8n-nodes-base.stickyNote",
      "typeVersion": 1,
      "position": [
        -1824,
        544
      ],
      "id": "11311e16-59ac-4971-91cd-f1533cdc45ad",
      "name": "Sticky Note2"
    },
    {
      "parameters": {
        "mode": "combine",
        "fieldsToMatchString": "ID",
        "options": {}
      },
      "type": "n8n-nodes-base.merge",
      "typeVersion": 3.2,
      "position": [
        448,
        864
      ],
      "id": "9ab07124-0a77-4bac-8c1a-7fb85c2ce7df",
      "name": "Merge PDF"
    },
    {
      "parameters": {
        "operation": "append",
        "documentId": {
          "__rl": true,
          "value": "={{ $vars.documents_doc }}",
          "mode": "id"
        },
        "sheetName": {
          "__rl": true,
          "value": "={{ $vars.documents_sheet_unformatted_pdf }}",
          "mode": "id"
        },
        "columns": {
          "mappingMode": "defineBelow",
          "value": {
            "Title": "={{ $('Final PDF').item.json.Title }}",
            "Source": "={{ $('Set Inputs').all()[0].json.Source }}",
            "Filename": "={{ $('Final PDF').item.json.Filename }}.pdf",
            "Last Modified": "={{ $('Final PDF').item.json['Last Modified'] }}",
            "Created Date": "={{ $('Final PDF').item.json['Created Date'] }}",
            "Job": "={{ $('Set Inputs').all()[0].json.Job }}",
            "Execution": "={{ $('Set Inputs').all()[0].json.Execution }}",
            "Hash": "={{ $('Final PDF').item.json.Hash }}",
            "Datetime": "={{ $now.toFormat(\"yyyy-MM-dd HH:mm:ss\") }}"
          },
          "matchingColumns": [
            "Source"
          ],
          "schema": [
            {
              "id": "Source",
              "displayName": "Source",
              "required": false,
              "defaultMatch": false,
              "display": true,
              "type": "string",
              "canBeUsedToMatch": true,
              "removed": false
            },
            {
              "id": "Datetime",
              "displayName": "Datetime",
              "required": false,
              "defaultMatch": false,
              "display": true,
              "type": "string",
              "canBeUsedToMatch": true,
              "removed": false
            },
            {
              "id": "Job",
              "displayName": "Job",
              "required": false,
              "defaultMatch": false,
              "display": true,
              "type": "string",
              "canBeUsedToMatch": true,
              "removed": false
            },
            {
              "id": "Execution",
              "displayName": "Execution",
              "required": false,
              "defaultMatch": false,
              "display": true,
              "type": "string",
              "canBeUsedToMatch": true,
              "removed": false
            },
            {
              "id": "Title",
              "displayName": "Title",
              "required": false,
              "defaultMatch": false,
              "display": true,
              "type": "string",
              "canBeUsedToMatch": true
            },
            {
              "id": "Created Date",
              "displayName": "Created Date",
              "required": false,
              "defaultMatch": false,
              "display": true,
              "type": "string",
              "canBeUsedToMatch": true,
              "removed": false
            },
            {
              "id": "Last Modified",
              "displayName": "Last Modified",
              "required": false,
              "defaultMatch": false,
              "display": true,
              "type": "string",
              "canBeUsedToMatch": true,
              "removed": false
            },
            {
              "id": "Hash",
              "displayName": "Hash",
              "required": false,
              "defaultMatch": false,
              "display": true,
              "type": "string",
              "canBeUsedToMatch": true,
              "removed": false
            },
            {
              "id": "Filename",
              "displayName": "Filename",
              "required": false,
              "defaultMatch": false,
              "display": true,
              "type": "string",
              "canBeUsedToMatch": true,
              "removed": false
            }
          ],
          "attemptToConvertTypes": false,
          "convertFieldsToString": false
        },
        "options": {}
      },
      "type": "n8n-nodes-base.googleSheets",
      "typeVersion": 4.7,
      "position": [
        1120,
        864
      ],
      "id": "6c14124c-cfcf-4ff4-a576-e3fbd3d1252d",
      "name": "Update Unformatted-PDF",
      "retryOnFail": true,
      "maxTries": 2,
      "waitBetweenTries": 5000
    },
    {
      "parameters": {
        "mode": "combine",
        "fieldsToMatchString": "ID",
        "options": {}
      },
      "type": "n8n-nodes-base.merge",
      "typeVersion": 3.2,
      "position": [
        896,
        1056
      ],
      "id": "c68e8284-a58a-48e7-b37a-a11752526a5b",
      "name": "Upload Merge"
    },
    {
      "parameters": {
        "assignments": {
          "assignments": [
            {
              "id": "db69125e-9e76-4c99-b7d8-074576d1e249",
              "name": "=ID",
              "value": "={{$execution.id}}",
              "type": "string"
            }
          ]
        },
        "options": {}
      },
      "type": "n8n-nodes-base.set",
      "typeVersion": 3.4,
      "position": [
        672,
        1152
      ],
      "id": "e2a3e755-8e68-431e-be64-5c65ea48a92d",
      "name": "Set ID"
    },
    {
      "parameters": {
        "conditions": {
          "options": {
            "caseSensitive": true,
            "leftValue": "",
            "typeValidation": "strict",
            "version": 2
          },
          "conditions": [
            {
              "id": "f26df12a-662b-47dd-8391-fc6ab7bdf6e2",
              "leftValue": "={{ $json.createdTime }}",
              "rightValue": "={{ $json.createdTime }}",
              "operator": {
                "type": "string",
                "operation": "notEmpty",
                "singleValue": true
              }
            }
          ],
          "combinator": "and"
        },
        "options": {}
      },
      "type": "n8n-nodes-base.if",
      "typeVersion": 2.2,
      "position": [
        448,
        1152
      ],
      "id": "5983cc26-d97c-4337-a34f-7497f05f676d",
      "name": "Success"
    },
    {
      "parameters": {
        "name": "={{ $('Set Inputs').item.json.Source.replace(/[?=]/g, '').replace(/https?:\\/\\/(www\\.)?/g, '').replace(/[\\/~]|\\.com|:|-|\\.|html/g, '').replace(/\\s/g, '') }}-{{ $now.toFormat('yyyyMMdd') }}.pdf",
        "driveId": {
          "__rl": true,
          "value": "=My Drive",
          "mode": "id"
        },
        "folderId": {
          "__rl": true,
          "value": "={{ $vars.folder_unformatted_pdf }}",
          "mode": "id"
        },
        "options": {}
      },
      "type": "n8n-nodes-base.googleDrive",
      "typeVersion": 3,
      "position": [
        224,
        1152
      ],
      "id": "e4229986-5608-4e5c-8c53-95094a8094d1",
      "name": "Upload-PDF",
      "retryOnFail": true,
      "maxTries": 2,
      "waitBetweenTries": 5000
    },
    {
      "parameters": {
        "operation": "append",
        "documentId": {
          "__rl": true,
          "value": "={{ $vars.documents_doc }}",
          "mode": "id"
        },
        "sheetName": {
          "__rl": true,
          "value": "={{ $vars.documents_sheet_formatted_pdf }}",
          "mode": "id"
        },
        "columns": {
          "mappingMode": "defineBelow",
          "value": {
            "Title": "={{ $('Final PDF').item.json.Title }}",
            "Source": "={{ $('Set Inputs').all()[0].json.Source }}",
            "Filename": "={{ $('Final PDF').item.json.Filename }}.txt",
            "Last Modified": "={{ $('Final PDF').item.json['Last Modified'] }}",
            "Created Date": "={{ $('Final PDF').item.json['Created Date'] }}",
            "Job": "={{ $('Set Inputs').all()[0].json.Job }}",
            "Execution": "={{ $('Set Inputs').all()[0].json.Execution }}",
            "Hash": "={{ $('Final PDF').item.json.Hash }}",
            "Datetime": "={{ $now.toFormat(\"yyyy-MM-dd HH:mm:ss\") }}"
          },
          "matchingColumns": [
            "Source"
          ],
          "schema": [
            {
              "id": "Source",
              "displayName": "Source",
              "required": false,
              "defaultMatch": false,
              "display": true,
              "type": "string",
              "canBeUsedToMatch": true,
              "removed": false
            },
            {
              "id": "Datetime",
              "displayName": "Datetime",
              "required": false,
              "defaultMatch": false,
              "display": true,
              "type": "string",
              "canBeUsedToMatch": true,
              "removed": false
            },
            {
              "id": "Job",
              "displayName": "Job",
              "required": false,
              "defaultMatch": false,
              "display": true,
              "type": "string",
              "canBeUsedToMatch": true,
              "removed": false
            },
            {
              "id": "Execution",
              "displayName": "Execution",
              "required": false,
              "defaultMatch": false,
              "display": true,
              "type": "string",
              "canBeUsedToMatch": true,
              "removed": false
            },
            {
              "id": "Title",
              "displayName": "Title",
              "required": false,
              "defaultMatch": false,
              "display": true,
              "type": "string",
              "canBeUsedToMatch": true
            },
            {
              "id": "Created Date",
              "displayName": "Created Date",
              "required": false,
              "defaultMatch": false,
              "display": true,
              "type": "string",
              "canBeUsedToMatch": true,
              "removed": false
            },
            {
              "id": "Last Modified",
              "displayName": "Last Modified",
              "required": false,
              "defaultMatch": false,
              "display": true,
              "type": "string",
              "canBeUsedToMatch": true,
              "removed": false
            },
            {
              "id": "Hash",
              "displayName": "Hash",
              "required": false,
              "defaultMatch": false,
              "display": true,
              "type": "string",
              "canBeUsedToMatch": true,
              "removed": false
            },
            {
              "id": "Filename",
              "displayName": "Filename",
              "required": false,
              "defaultMatch": false,
              "display": true,
              "type": "string",
              "canBeUsedToMatch": true,
              "removed": false
            }
          ],
          "attemptToConvertTypes": false,
          "convertFieldsToString": false
        },
        "options": {}
      },
      "type": "n8n-nodes-base.googleSheets",
      "typeVersion": 4.7,
      "position": [
        1120,
        672
      ],
      "id": "0e5c1303-c461-4700-beb0-c2d04a506d96",
      "name": "Update Formatted-PDF",
      "retryOnFail": true,
      "maxTries": 2,
      "waitBetweenTries": 5000
    },
    {
      "parameters": {
        "operation": "createFromText",
        "content": "={{ $json.data }}",
        "name": "={{ $json.Filename }}.txt",
        "driveId": {
          "__rl": true,
          "value": "=My Drive",
          "mode": "id"
        },
        "folderId": {
          "__rl": true,
          "value": "={{ $vars.folder_formatted_pdf }}",
          "mode": "id"
        },
        "options": {}
      },
      "type": "n8n-nodes-base.googleDrive",
      "typeVersion": 3,
      "position": [
        896,
        672
      ],
      "id": "319c0fd2-4b7b-4dae-931d-2028078cc054",
      "name": "Upload-Formatted-PDF",
      "retryOnFail": true,
      "maxTries": 2,
      "waitBetweenTries": 5000
    },
    {
      "parameters": {
        "assignments": {
          "assignments": [
            {
              "id": "0779c1ce-d087-42d3-80a0-1d18360ca697",
              "name": "ID",
              "value": "={{$execution.id}}",
              "type": "string"
            },
            {
              "id": "bd693022-4fc4-4c70-9b86-6b44c5f49303",
              "name": "Title",
              "value": "={{ $json.Title }}",
              "type": "string"
            },
            {
              "id": "c362607c-1195-4131-b3b5-f47952e45692",
              "name": "Created Date",
              "value": "={{ $json.CreationDate }}",
              "type": "string"
            },
            {
              "id": "feabf9d3-b3ca-4270-8263-cce8dd7a8e13",
              "name": "Last Modified",
              "value": "={{ $json.ModDate }}",
              "type": "string"
            },
            {
              "id": "1b46b873-e267-4ac6-8e06-b9b347c4b308",
              "name": "Etag",
              "value": "",
              "type": "string"
            },
            {
              "id": "4d7cfbef-f020-417a-96e6-a876f400af2d",
              "name": "Hash",
              "value": "={{ $json.hash }}",
              "type": "string"
            },
            {
              "id": "cd248931-97e7-4c94-8ebd-7c9077a5a1a8",
              "name": "Filename",
              "value": "={{ $json.Filename }}",
              "type": "string"
            },
            {
              "id": "1a1467b2-4369-4e6d-b6a0-9f7ddfa7db17",
              "name": "data",
              "value": "={{ $json.data }}",
              "type": "string"
            }
          ]
        },
        "options": {}
      },
      "type": "n8n-nodes-base.set",
      "typeVersion": 3.4,
      "position": [
        672,
        864
      ],
      "id": "2dc6a9e8-6726-4a2f-9fc5-9ec3b49f0864",
      "name": "Final PDF"
    },
    {
      "parameters": {
        "assignments": {
          "assignments": [
            {
              "id": "0f0182c6-4362-4af6-bda7-d72a82e6b9b3",
              "name": "ID",
              "value": "={{$execution.id}}",
              "type": "string"
            },
            {
              "id": "cc073a9f-7934-4039-8e77-d288234e5792",
              "name": "Title",
              "value": "={{ $json.text.split('\\n')[0] ?? $json.data.split('\\n')[0]}}",
              "type": "string"
            },
            {
              "id": "c362607c-1195-4131-b3b5-f47952e45692",
              "name": "CreationDate",
              "value": "={{ $('Extract PDF Data').all()[0].json.info.CreationDate }}",
              "type": "string"
            },
            {
              "id": "feabf9d3-b3ca-4270-8263-cce8dd7a8e13",
              "name": "ModDate",
              "value": "={{ $('Extract PDF Data').all()[0].json.info.ModDate }}",
              "type": "string"
            },
            {
              "id": "2ed3e942-9a58-4a78-b84d-f2bd05ee1783",
              "name": "Filename",
              "value": "={{ $('Set Inputs').all()[0].json.Source.replace(/[?=]/g, '').replace(/https?:\\/\\/(www\\.)?/g, '').replace(/[\\/~]|\\.com|:|-|\\.|html/g, '').replace(/\\s/g, '') }}-{{ $now.toFormat('yyyyMMdd') }}",
              "type": "string"
            },
            {
              "id": "78c0c8aa-38c9-4081-93cb-affeb0323887",
              "name": "data",
              "value": "={{ $json.text ?? json.data }}",
              "type": "string"
            }
          ]
        },
        "options": {}
      },
      "type": "n8n-nodes-base.set",
      "typeVersion": 3.4,
      "position": [
        224,
        960
      ],
      "id": "e4e9ab4b-6d79-4cc9-9e56-540a7ed84dcc",
      "name": "Set PDF Data"
    },
    {
      "parameters": {
        "assignments": {
          "assignments": [
            {
              "id": "b2cd3550-5655-4c6d-93d5-5ff61683c966",
              "name": "ID",
              "value": "={{$execution.id}}",
              "type": "string"
            },
            {
              "id": "17d95b31-278d-40ca-922c-f315025e92f8",
              "name": "hash",
              "value": "={{ $json.data }}",
              "type": "string"
            }
          ]
        },
        "options": {}
      },
      "type": "n8n-nodes-base.set",
      "typeVersion": 3.4,
      "position": [
        224,
        768
      ],
      "id": "2b3e4621-2aa4-4d38-9ed9-aa8e4b442d06",
      "name": "Set PDF Hash"
    },
    {
      "parameters": {
        "binaryData": true,
        "type": "SHA3-256"
      },
      "type": "n8n-nodes-base.crypto",
      "typeVersion": 1,
      "position": [
        0,
        768
      ],
      "id": "3361e834-e515-4b99-9758-fd14e8a1e37d",
      "name": "PDF Hash"
    },
    {
      "parameters": {
        "operation": "pdf",
        "options": {}
      },
      "type": "n8n-nodes-base.extractFromFile",
      "typeVersion": 1,
      "position": [
        0,
        960
      ],
      "id": "b1ad8a0a-3a15-4adc-b5dc-bf461b5b3e58",
      "name": "Extract PDF Data",
      "retryOnFail": true,
      "maxTries": 2,
      "waitBetweenTries": 5000
    },
    {
      "parameters": {
        "html": "={{ $json.body }}",
        "options": {
          "ignore": "a,img,nav,header,footer,script,style,form,button,svg"
        }
      },
      "id": "f40c5f3b-c947-410d-92c5-44dfa73ae801",
      "name": "Convert HTML to Markdown",
      "type": "n8n-nodes-base.markdown",
      "position": [
        896,
        480
      ],
      "typeVersion": 1,
      "retryOnFail": true,
      "waitBetweenTries": 5000,
      "maxTries": 4
    },
    {
      "parameters": {
        "operation": "createFromText",
        "content": "={{ $json.data }}",
        "name": "={{ $json.Filename }}",
        "driveId": {
          "__rl": true,
          "value": "=My Drive",
          "mode": "id"
        },
        "folderId": {
          "__rl": true,
          "value": "={{ $vars.folder_formatted_html }}",
          "mode": "id"
        },
        "options": {}
      },
      "type": "n8n-nodes-base.googleDrive",
      "typeVersion": 3,
      "position": [
        1792,
        480
      ],
      "id": "7e5e7178-d9dc-4b4f-a2cd-827fb997892e",
      "name": "Upload-Formatted-HTML",
      "retryOnFail": true,
      "maxTries": 2,
      "waitBetweenTries": 5000
    },
    {
      "parameters": {
        "jsCode": "// items: [{ json: { data: '...markdown...' } }, ...]\n\nreturn items.map(item => {\n  let md = item.json.data || '';\n\n  // Normalize line endings\n  md = md.replace(/\\r\\n/g, '\\n');\n\n  const navJunkPatterns = [\n    /you are here:/i,\n    /back to top/i,\n    /cookie/i,\n    /privacy policy/i,\n    /terms of (use|service)/i,\n    /all rights reserved/i,\n    /accept cookies/i,\n    /enable javascript/i,\n  ];\n\n  const lines = md.split('\\n');\n  const cleanedLines = [];\n\n  for (let raw of lines) {\n    let line = raw;\n    const trimmed = line.trim();\n\n    // 1. Keep blank lines (we'll collapse later)\n    if (!trimmed) {\n      cleanedLines.push('');\n      continue;\n    }\n\n    // 2. Drop YAML/frontmatter / horizontal rules like \"---\"\n    if (/^---+$/.test(trimmed)) continue;\n\n    // 3. Drop pure punctuation separators (***, ___, etc.)\n    if (/^[\\-\\*_~`]+$/.test(trimmed)) continue;\n\n    // 4. Detect markdown table-ish lines\n    const isTableRow = /^\\s*\\|.*\\|\\s*$/.test(trimmed);\n    const isTableSeparator = /^\\s*\\|?\\s*:?-{2,}.*\\|?\\s*$/.test(trimmed);\n\n    // If it's clearly a table separator row, drop it\n    if (isTableSeparator) continue;\n\n    // Optional: If you want to drop ALL table rows, uncomment:\n    // if (isTableRow) continue;\n\n    // 5. Skip obvious nav/footer/legal junk\n    if (navJunkPatterns.some(re => re.test(trimmed))) continue;\n\n    // 6. Skip tiny non-heading, non-list UI fragments\n    const wordCount = trimmed.split(/\\s+/).length;\n    const isHeadingOrList = /^(#{1,6}\\s|\\* |-|\\d+\\.)/.test(trimmed);\n    if (\n      wordCount <= 3 &&\n      !isHeadingOrList &&\n      !/[.!?]$/.test(trimmed) // not a full sentence\n    ) {\n      // e.g. \"Filter:\", \"Submit Search\", \"Login\"\n      continue;\n    }\n\n    // 7. Normalize internal spacing a bit\n    line = line.replace(/[ \\t]{2,}/g, ' ');\n\n    cleanedLines.push(line);\n  }\n\n  // 8. Collapse multiple blank lines into a single blank line\n  const cleaned = cleanedLines\n    .join('\\n')\n    .replace(/\\n{3,}/g, '\\n\\n')\n    .trim();\n\n  item.json.cleanedMarkdown = cleaned;\n  return item;\n});"
      },
      "type": "n8n-nodes-base.code",
      "typeVersion": 2,
      "position": [
        1120,
        480
      ],
      "id": "c54e5bd9-6382-4911-8d0e-6b3d5bca3831",
      "name": "Clean Markdown",
      "retryOnFail": true,
      "maxTries": 2,
      "waitBetweenTries": 5000
    },
    {
      "parameters": {
        "operation": "createFromText",
        "content": "={{ $json.data }}",
        "name": "={{ $json.Filename }}",
        "driveId": {
          "__rl": true,
          "value": "=My Drive",
          "mode": "id"
        },
        "folderId": {
          "__rl": true,
          "value": "={{ $vars.folder_unformatted_html }}",
          "mode": "id"
        },
        "options": {}
      },
      "type": "n8n-nodes-base.googleDrive",
      "typeVersion": 3,
      "position": [
        1120,
        288
      ],
      "id": "3b80e6c4-d5ac-4995-b6ff-5dc6dc89aeb4",
      "name": "Upload-Unformatted-HTML",
      "retryOnFail": true,
      "maxTries": 2,
      "waitBetweenTries": 5000
    },
    {
      "parameters": {
        "operation": "append",
        "documentId": {
          "__rl": true,
          "value": "={{ $vars.documents_doc }}",
          "mode": "id"
        },
        "sheetName": {
          "__rl": true,
          "value": "={{ $vars.documents_sheet_unformatted_html }}",
          "mode": "id"
        },
        "columns": {
          "mappingMode": "defineBelow",
          "value": {
            "Source": "={{ $('Set Unformatted HTML').item.json.Source }}",
            "Title": "={{ $('Set Unformatted HTML').item.json.Title }}",
            "Last Modified": "={{ $('Set Unformatted HTML').item.json['Last Modified'] }}",
            "Etag": "={{ $('Set Unformatted HTML').item.json.Etag }}",
            "Filename": "={{ $('Set Unformatted HTML').item.json.Filename }}",
            "Job": "={{ $('Set Inputs').all()[0].json.Job }}",
            "Execution": "={{ $('Set Inputs').all()[0].json.Execution }}",
            "Hash": "={{ $('Set Unformatted HTML').item.json.Hash }}",
            "Datetime": "={{ $now.toFormat(\"yyyy-MM-dd HH:mm:ss\") }}"
          },
          "matchingColumns": [
            "Source"
          ],
          "schema": [
            {
              "id": "Source",
              "displayName": "Source",
              "required": false,
              "defaultMatch": false,
              "display": true,
              "type": "string",
              "canBeUsedToMatch": true,
              "removed": false
            },
            {
              "id": "Datetime",
              "displayName": "Datetime",
              "required": false,
              "defaultMatch": false,
              "display": true,
              "type": "string",
              "canBeUsedToMatch": true,
              "removed": false
            },
            {
              "id": "Job",
              "displayName": "Job",
              "required": false,
              "defaultMatch": false,
              "display": true,
              "type": "string",
              "canBeUsedToMatch": true,
              "removed": false
            },
            {
              "id": "Execution",
              "displayName": "Execution",
              "required": false,
              "defaultMatch": false,
              "display": true,
              "type": "string",
              "canBeUsedToMatch": true,
              "removed": false
            },
            {
              "id": "Title",
              "displayName": "Title",
              "required": false,
              "defaultMatch": false,
              "display": true,
              "type": "string",
              "canBeUsedToMatch": true
            },
            {
              "id": "Last Modified",
              "displayName": "Last Modified",
              "required": false,
              "defaultMatch": false,
              "display": true,
              "type": "string",
              "canBeUsedToMatch": true,
              "removed": false
            },
            {
              "id": "Etag",
              "displayName": "Etag",
              "required": false,
              "defaultMatch": false,
              "display": true,
              "type": "string",
              "canBeUsedToMatch": true,
              "removed": false
            },
            {
              "id": "Hash",
              "displayName": "Hash",
              "required": false,
              "defaultMatch": false,
              "display": true,
              "type": "string",
              "canBeUsedToMatch": true,
              "removed": false
            },
            {
              "id": "Filename",
              "displayName": "Filename",
              "required": false,
              "defaultMatch": false,
              "display": true,
              "type": "string",
              "canBeUsedToMatch": true,
              "removed": false
            }
          ],
          "attemptToConvertTypes": false,
          "convertFieldsToString": false
        },
        "options": {}
      },
      "type": "n8n-nodes-base.googleSheets",
      "typeVersion": 4.7,
      "position": [
        1344,
        288
      ],
      "id": "258bb421-227b-4081-852f-521ed81c783b",
      "name": "Update Unformatted-HTML",
      "retryOnFail": true,
      "maxTries": 2,
      "waitBetweenTries": 5000
    },
    {
      "parameters": {
        "assignments": {
          "assignments": [
            {
              "id": "f24c5582-740e-4657-9b9b-80f7c08823e8",
              "name": "data",
              "value": "={{ $json.cleanedMarkdown }}",
              "type": "string"
            },
            {
              "id": "bee9eb66-6449-4903-943c-a2ebe4e55e45",
              "name": "Source",
              "value": "={{ $('Set Upload').item.json.Source }}",
              "type": "string"
            },
            {
              "id": "e4e2a0f4-4082-4d33-8208-129948b3de1d",
              "name": "Title",
              "value": "={{ $('Set Upload').item.json.Title }}",
              "type": "string"
            },
            {
              "id": "7c5adf3b-694a-41d6-a931-aaf768f7b5a0",
              "name": "Last Modified",
              "value": "={{ $('Set Upload').item.json['Last Modified'] }}",
              "type": "string"
            },
            {
              "id": "948ed494-c0eb-4e5b-a0f2-e5102d84dbf6",
              "name": "Etag",
              "value": "={{ $('Set Upload').item.json.Etag }}",
              "type": "string"
            },
            {
              "id": "57aa300d-61c6-40b2-8032-41992cb08847",
              "name": "Hash",
              "value": "={{ $json.hash }}",
              "type": "string"
            },
            {
              "id": "1ba432ca-2226-44ab-8cdd-a70ca09ea879",
              "name": "Filename",
              "value": "={{ $('Set Upload').item.json.filename }}.md",
              "type": "string"
            }
          ]
        },
        "options": {}
      },
      "type": "n8n-nodes-base.set",
      "typeVersion": 3.4,
      "position": [
        1568,
        480
      ],
      "id": "90146cfe-8d45-4ae8-95e2-3ede90026175",
      "name": "Set Formatted HTML"
    },
    {
      "parameters": {
        "assignments": {
          "assignments": [
            {
              "id": "f24c5582-740e-4657-9b9b-80f7c08823e8",
              "name": "data",
              "value": "={{ $json.body }}",
              "type": "string"
            },
            {
              "id": "29f7a3ae-1cde-487f-b700-9fe615bc0d64",
              "name": "Source",
              "value": "={{ $json.Source }}",
              "type": "string"
            },
            {
              "id": "e4e2a0f4-4082-4d33-8208-129948b3de1d",
              "name": "Title",
              "value": "={{ $json.Title }}",
              "type": "string"
            },
            {
              "id": "7c5adf3b-694a-41d6-a931-aaf768f7b5a0",
              "name": "Last Modified",
              "value": "={{ $json['Last Modified'] }}",
              "type": "string"
            },
            {
              "id": "948ed494-c0eb-4e5b-a0f2-e5102d84dbf6",
              "name": "Etag",
              "value": "={{ $json.Etag }}",
              "type": "string"
            },
            {
              "id": "57aa300d-61c6-40b2-8032-41992cb08847",
              "name": "Hash",
              "value": "={{ $json.hash }}",
              "type": "string"
            },
            {
              "id": "1ba432ca-2226-44ab-8cdd-a70ca09ea879",
              "name": "Filename",
              "value": "={{ $json.filename }}.html",
              "type": "string"
            }
          ]
        },
        "options": {}
      },
      "type": "n8n-nodes-base.set",
      "typeVersion": 3.4,
      "position": [
        896,
        288
      ],
      "id": "4054735c-7e1a-42d7-8d29-f54cbcb50459",
      "name": "Set Unformatted HTML"
    },
    {
      "parameters": {
        "operation": "append",
        "documentId": {
          "__rl": true,
          "value": "={{ $vars.scrape_doc }}",
          "mode": "id"
        },
        "sheetName": {
          "__rl": true,
          "value": "={{ $vars.scrape_sheet_output }} ",
          "mode": "id"
        },
        "columns": {
          "mappingMode": "defineBelow",
          "value": {
            "Title": "={{ $('Final PDF').item.json.Title }}",
            "Source": "={{ $('Set Inputs').all()[0].json.Source }}",
            "Filename": "={{ $('Final PDF').item.json.Filename }}.txt",
            "Last Modified": "={{ $('Final PDF').item.json['Last Modified'] }}",
            "Created Date": "={{ $('Final PDF').item.json['Created Date'] }}",
            "Job": "={{ $('Set Inputs').all()[0].json.Job }}",
            "Execution": "={{ $('Set Inputs').all()[0].json.Execution }}",
            "Hash": "={{ $('Final PDF').item.json.Hash }}",
            "Datetime": "={{ $now.toFormat(\"yyyy-MM-dd HH:mm:ss\") }}"
          },
          "matchingColumns": [
            "Source"
          ],
          "schema": [
            {
              "id": "Source",
              "displayName": "Source",
              "required": false,
              "defaultMatch": false,
              "display": true,
              "type": "string",
              "canBeUsedToMatch": true,
              "removed": false
            },
            {
              "id": "Datetime",
              "displayName": "Datetime",
              "required": false,
              "defaultMatch": false,
              "display": true,
              "type": "string",
              "canBeUsedToMatch": true,
              "removed": false
            },
            {
              "id": "Job",
              "displayName": "Job",
              "required": false,
              "defaultMatch": false,
              "display": true,
              "type": "string",
              "canBeUsedToMatch": true,
              "removed": false
            },
            {
              "id": "Execution",
              "displayName": "Execution",
              "required": false,
              "defaultMatch": false,
              "display": true,
              "type": "string",
              "canBeUsedToMatch": true,
              "removed": false
            },
            {
              "id": "Title",
              "displayName": "Title",
              "required": false,
              "defaultMatch": false,
              "display": true,
              "type": "string",
              "canBeUsedToMatch": true
            },
            {
              "id": "Created Date",
              "displayName": "Created Date",
              "required": false,
              "defaultMatch": false,
              "display": true,
              "type": "string",
              "canBeUsedToMatch": true,
              "removed": false
            },
            {
              "id": "Last Modified",
              "displayName": "Last Modified",
              "required": false,
              "defaultMatch": false,
              "display": true,
              "type": "string",
              "canBeUsedToMatch": true,
              "removed": false
            },
            {
              "id": "Etag",
              "displayName": "Etag",
              "required": false,
              "defaultMatch": false,
              "display": true,
              "type": "string",
              "canBeUsedToMatch": true,
              "removed": false
            },
            {
              "id": "Hash",
              "displayName": "Hash",
              "required": false,
              "defaultMatch": false,
              "display": true,
              "type": "string",
              "canBeUsedToMatch": true,
              "removed": false
            },
            {
              "id": "Filename",
              "displayName": "Filename",
              "required": false,
              "defaultMatch": false,
              "display": true,
              "type": "string",
              "canBeUsedToMatch": true,
              "removed": false
            }
          ],
          "attemptToConvertTypes": false,
          "convertFieldsToString": false
        },
        "options": {}
      },
      "type": "n8n-nodes-base.googleSheets",
      "typeVersion": 4.7,
      "position": [
        1120,
        1152
      ],
      "id": "eefa0281-ad88-40af-a630-72da9168a7f3",
      "name": "Update Scrape-Output (PDF)",
      "retryOnFail": true,
      "maxTries": 2,
      "waitBetweenTries": 5000
    },
    {
      "parameters": {
        "operation": "append",
        "documentId": {
          "__rl": true,
          "value": "={{ $vars.scrape_doc }}",
          "mode": "id"
        },
        "sheetName": {
          "__rl": true,
          "value": "={{ $vars.scrape_sheet_output }} ",
          "mode": "id"
        },
        "columns": {
          "mappingMode": "defineBelow",
          "value": {
            "Title": "={{ $('Set Formatted HTML').item.json.Title }}",
            "Source": "={{ $('Set Formatted HTML').item.json.Source }}",
            "Last Modified": "={{ $('Set Formatted HTML').item.json['Last Modified'] }}",
            "Etag": "={{ $('Set Formatted HTML').item.json.Etag }}",
            "Filename": "={{ $('Set Formatted HTML').item.json.Filename }}",
            "Job": "={{ $('Set Inputs').all()[0].json.Job }}",
            "Execution": "={{ $('Set Inputs').all()[0].json.Execution }}",
            "Hash": "={{ $('Set Formatted HTML').item.json.Hash }}",
            "Datetime": "={{ $now.toFormat(\"yyyy-MM-dd HH:mm:ss\") }}"
          },
          "matchingColumns": [],
          "schema": [
            {
              "id": "Source",
              "displayName": "Source",
              "required": false,
              "defaultMatch": false,
              "display": true,
              "type": "string",
              "canBeUsedToMatch": true
            },
            {
              "id": "Datetime",
              "displayName": "Datetime",
              "required": false,
              "defaultMatch": false,
              "display": true,
              "type": "string",
              "canBeUsedToMatch": true,
              "removed": false
            },
            {
              "id": "Job",
              "displayName": "Job",
              "required": false,
              "defaultMatch": false,
              "display": true,
              "type": "string",
              "canBeUsedToMatch": true
            },
            {
              "id": "Execution",
              "displayName": "Execution",
              "required": false,
              "defaultMatch": false,
              "display": true,
              "type": "string",
              "canBeUsedToMatch": true
            },
            {
              "id": "Title",
              "displayName": "Title",
              "required": false,
              "defaultMatch": false,
              "display": true,
              "type": "string",
              "canBeUsedToMatch": true
            },
            {
              "id": "Created Date",
              "displayName": "Created Date",
              "required": false,
              "defaultMatch": false,
              "display": true,
              "type": "string",
              "canBeUsedToMatch": true
            },
            {
              "id": "Last Modified",
              "displayName": "Last Modified",
              "required": false,
              "defaultMatch": false,
              "display": true,
              "type": "string",
              "canBeUsedToMatch": true
            },
            {
              "id": "Etag",
              "displayName": "Etag",
              "required": false,
              "defaultMatch": false,
              "display": true,
              "type": "string",
              "canBeUsedToMatch": true
            },
            {
              "id": "Hash",
              "displayName": "Hash",
              "required": false,
              "defaultMatch": false,
              "display": true,
              "type": "string",
              "canBeUsedToMatch": true,
              "removed": false
            },
            {
              "id": "Filename",
              "displayName": "Filename",
              "required": false,
              "defaultMatch": false,
              "display": true,
              "type": "string",
              "canBeUsedToMatch": true
            }
          ],
          "attemptToConvertTypes": false,
          "convertFieldsToString": false
        },
        "options": {}
      },
      "type": "n8n-nodes-base.googleSheets",
      "typeVersion": 4.7,
      "position": [
        2016,
        576
      ],
      "id": "9729c40e-6997-4df0-b0c3-e740e900956b",
      "name": "Update Scrape-Output (HTML)",
      "retryOnFail": true,
      "maxTries": 2,
      "waitBetweenTries": 5000
    },
    {
      "parameters": {
        "assignments": {
          "assignments": [
            {
              "id": "fca835c3-7013-4ad0-b7cf-ebe988a15a79",
              "name": "body",
              "value": "={{ $('Set Source').all()[0].json.body }}",
              "type": "string"
            },
            {
              "id": "c498557d-3422-4f66-8de0-90fae1221c01",
              "name": "Source",
              "value": "={{ $('Set Source').all()[0].json.Source }}",
              "type": "string"
            },
            {
              "id": "7b8edf18-68a6-4db7-ad07-8864ae56d26f",
              "name": "Title",
              "value": "={{ $('Set Source').all()[0].json.title }}",
              "type": "string"
            },
            {
              "id": "346568cf-f069-4f88-a12d-56e1977eee21",
              "name": "Last Modified",
              "value": "={{ $('Set Source').all()[0].json['last-modified'] }}",
              "type": "string"
            },
            {
              "id": "bdc830be-3b71-43d9-bfbd-248a6d6dff14",
              "name": "=Etag",
              "value": "={{ $('Set Source').all()[0].json.etag }}",
              "type": "string"
            },
            {
              "id": "d4e85ac0-9e42-4118-90d8-0b76c530971d",
              "name": "filename",
              "value": "={{ $('Set Source').all()[0].json.Source.replace(/[?=]/g, '').replace(/https?:\\/\\/(www\\.)?/g, '').replace(/\\/|\\.com|:|-|\\.|html/g, '').replace(/\\s/g, '') }}-{{ $now.toFormat('yyyyMMdd') }}",
              "type": "string"
            }
          ]
        },
        "options": {}
      },
      "type": "n8n-nodes-base.set",
      "typeVersion": 3.4,
      "position": [
        448,
        384
      ],
      "id": "a2ec0ca3-0cf3-4507-ba05-181478843b59",
      "name": "Set Upload"
    },
    {
      "parameters": {
        "operation": "append",
        "documentId": {
          "__rl": true,
          "value": "={{ $vars.documents_doc }}",
          "mode": "id"
        },
        "sheetName": {
          "__rl": true,
          "value": "={{ $vars.documents_sheet_formatted_html }}",
          "mode": "id"
        },
        "columns": {
          "mappingMode": "defineBelow",
          "value": {
            "Source": "={{ $('Set Formatted HTML').item.json.Source }}",
            "Title": "={{ $('Set Formatted HTML').item.json.Title }}",
            "Last Modified": "={{ $('Set Formatted HTML').item.json['Last Modified'] }}",
            "Etag": "={{ $('Set Formatted HTML').item.json.Etag }}",
            "Filename": "={{ $('Set Formatted HTML').item.json.Filename }}",
            "Job": "={{ $('Set Inputs').all()[0].json.Job }}",
            "Execution": "={{ $('Set Inputs').all()[0].json.Execution }}",
            "Hash": "={{ $('Set Formatted HTML').item.json.Hash }}",
            "Datetime": "={{ $now.toFormat(\"yyyy-MM-dd HH:mm:ss\") }}"
          },
          "matchingColumns": [
            "Source"
          ],
          "schema": [
            {
              "id": "Source",
              "displayName": "Source",
              "required": false,
              "defaultMatch": false,
              "display": true,
              "type": "string",
              "canBeUsedToMatch": true,
              "removed": false
            },
            {
              "id": "Datetime",
              "displayName": "Datetime",
              "required": false,
              "defaultMatch": false,
              "display": true,
              "type": "string",
              "canBeUsedToMatch": true,
              "removed": false
            },
            {
              "id": "Job",
              "displayName": "Job",
              "required": false,
              "defaultMatch": false,
              "display": true,
              "type": "string",
              "canBeUsedToMatch": true,
              "removed": false
            },
            {
              "id": "Execution",
              "displayName": "Execution",
              "required": false,
              "defaultMatch": false,
              "display": true,
              "type": "string",
              "canBeUsedToMatch": true,
              "removed": false
            },
            {
              "id": "Title",
              "displayName": "Title",
              "required": false,
              "defaultMatch": false,
              "display": true,
              "type": "string",
              "canBeUsedToMatch": true
            },
            {
              "id": "Last Modified",
              "displayName": "Last Modified",
              "required": false,
              "defaultMatch": false,
              "display": true,
              "type": "string",
              "canBeUsedToMatch": true,
              "removed": false
            },
            {
              "id": "Etag",
              "displayName": "Etag",
              "required": false,
              "defaultMatch": false,
              "display": true,
              "type": "string",
              "canBeUsedToMatch": true,
              "removed": false
            },
            {
              "id": "Hash",
              "displayName": "Hash",
              "required": false,
              "defaultMatch": false,
              "display": true,
              "type": "string",
              "canBeUsedToMatch": true,
              "removed": false
            },
            {
              "id": "Filename",
              "displayName": "Filename",
              "required": false,
              "defaultMatch": false,
              "display": true,
              "type": "string",
              "canBeUsedToMatch": true,
              "removed": false
            }
          ],
          "attemptToConvertTypes": false,
          "convertFieldsToString": false
        },
        "options": {}
      },
      "type": "n8n-nodes-base.googleSheets",
      "typeVersion": 4.7,
      "position": [
        2016,
        384
      ],
      "id": "4df88a99-7420-4fc4-978a-0e206dde0b16",
      "name": "Update Formatted-HTML",
      "retryOnFail": true,
      "maxTries": 2,
      "waitBetweenTries": 5000
    },
    {
      "parameters": {
        "assignments": {
          "assignments": []
        },
        "options": {}
      },
      "type": "n8n-nodes-base.set",
      "typeVersion": 3.4,
      "position": [
        2240,
        576
      ],
      "id": "fd08b7b9-bf7a-4a97-96ea-024e78269fe6",
      "name": "Set Output (HTML Scrape)",
      "executeOnce": true
    },
    {
      "parameters": {
        "assignments": {
          "assignments": []
        },
        "options": {}
      },
      "type": "n8n-nodes-base.set",
      "typeVersion": 3.4,
      "position": [
        1344,
        1152
      ],
      "id": "c79e1e83-d339-4c1b-a00c-d686ca4631d1",
      "name": "Set Output (PDF Scrape)",
      "executeOnce": true
    },
    {
      "parameters": {
        "assignments": {
          "assignments": [
            {
              "id": "id-1",
              "name": "fileSizeMB",
              "value": "={{ (parseInt($json.headers['content-length']) / 1048576).toFixed(2) }}",
              "type": "string"
            },
            {
              "id": "id-2",
              "name": "fileSizeBytes",
              "value": "={{ parseInt($json.headers['content-length']) }}",
              "type": "number"
            }
          ]
        },
        "includeOtherFields": true,
        "options": {}
      },
      "id": "20354c55-8479-4c44-9db4-5c6ab8812693",
      "name": "Calculate File Size",
      "type": "n8n-nodes-base.set",
      "typeVersion": 3.4,
      "position": [
        -448,
        864
      ]
    },
    {
      "parameters": {
        "operation": "append",
        "documentId": {
          "__rl": true,
          "value": "={{ $vars.manager_doc }}",
          "mode": "id"
        },
        "sheetName": {
          "__rl": true,
          "value": "={{ $vars.manager_sheet_error }}",
          "mode": "id"
        },
        "columns": {
          "mappingMode": "defineBelow",
          "value": {
            "Source": "={{ $('Set Inputs').all()[0].json.Source }}",
            "Job": "={{ $('Set Inputs').all()[0].json.Job }}",
            "Execution": "={{ $('Set Inputs').all()[0].json.Execution }}",
            "Error": "=PDF Size - {{ $json.fileSizeMB }}mb",
            "Datetime": "={{ $now.toFormat(\"yyyy-MM-dd HH:mm:ss\") }}"
          },
          "matchingColumns": [
            "Source"
          ],
          "schema": [
            {
              "id": "Source",
              "displayName": "Source",
              "required": false,
              "defaultMatch": false,
              "display": true,
              "type": "string",
              "canBeUsedToMatch": true,
              "removed": false
            },
            {
              "id": "Datetime",
              "displayName": "Datetime",
              "required": false,
              "defaultMatch": false,
              "display": true,
              "type": "string",
              "canBeUsedToMatch": true,
              "removed": false
            },
            {
              "id": "Error",
              "displayName": "Error",
              "required": false,
              "defaultMatch": false,
              "display": true,
              "type": "string",
              "canBeUsedToMatch": true,
              "removed": false
            },
            {
              "id": "Job",
              "displayName": "Job",
              "required": false,
              "defaultMatch": false,
              "display": true,
              "type": "string",
              "canBeUsedToMatch": true
            },
            {
              "id": "Execution",
              "displayName": "Execution",
              "required": false,
              "defaultMatch": false,
              "display": true,
              "type": "string",
              "canBeUsedToMatch": true
            }
          ],
          "attemptToConvertTypes": false,
          "convertFieldsToString": false
        },
        "options": {}
      },
      "type": "n8n-nodes-base.googleSheets",
      "typeVersion": 4.7,
      "position": [
        0,
        576
      ],
      "id": "a064a184-44db-4c3a-bd63-8fc00926c3d0",
      "name": "Append Error (PDF Size)",
      "retryOnFail": true,
      "maxTries": 2,
      "waitBetweenTries": 5000
    },
    {
      "parameters": {
        "assignments": {
          "assignments": []
        },
        "options": {}
      },
      "type": "n8n-nodes-base.set",
      "typeVersion": 3.4,
      "position": [
        672,
        576
      ],
      "id": "6504bf41-a094-4fd7-ad25-e08ba5f4861c",
      "name": "Set Workflow Output (PDF Error)2",
      "executeOnce": true
    },
    {
      "parameters": {
        "conditions": {
          "options": {
            "caseSensitive": true,
            "leftValue": "",
            "typeValidation": "strict",
            "version": 2
          },
          "conditions": [
            {
              "id": "id-1",
              "leftValue": "={{ (parseInt($json.headers['content-length']) / 1048576) > 15 }}",
              "operator": {
                "type": "boolean",
                "operation": "true"
              }
            }
          ],
          "combinator": "and"
        },
        "options": {}
      },
      "id": "623c9f22-58d3-4073-9ba3-9a6ce808a809",
      "name": "Greater Than 15mb",
      "type": "n8n-nodes-base.if",
      "typeVersion": 2.2,
      "position": [
        -224,
        864
      ]
    },
    {
      "parameters": {
        "content": "\n\n\n\n\n\n\n\n\n\n\n\n\n\nOptional Workflow:\nProcess large documents with Transloadit OCR service",
        "height": 272,
        "width": 192,
        "color": 7
      },
      "type": "n8n-nodes-base.stickyNote",
      "typeVersion": 1,
      "position": [
        400,
        576
      ],
      "id": "7c8f7787-42e0-4351-9616-79bda3d6edd5",
      "name": "Sticky Note3"
    },
    {
      "parameters": {
        "assignments": {
          "assignments": [
            {
              "id": "530e4c34-5afd-481a-a17d-5c8ec4e129bb",
              "name": "Source",
              "value": "={{ $('Set Inputs').all()[0].json.Source }}",
              "type": "string"
            },
            {
              "id": "7f3c015e-d258-48cd-889f-1b42aeb416ce",
              "name": "=Job",
              "value": "={{ $('Set Inputs').all()[0].json.Job }}",
              "type": "string"
            },
            {
              "id": "4f9db832-b1fe-46cf-9791-69205ecb18d5",
              "name": "Execution",
              "value": "={{ $('Set Inputs').all()[0].json.Execution }}",
              "type": "string"
            }
          ]
        },
        "options": {}
      },
      "type": "n8n-nodes-base.set",
      "typeVersion": 3.4,
      "position": [
        224,
        576
      ],
      "id": "58ab2403-fbf1-46d1-8eb1-8921e345513c",
      "name": "Set TransloaditOCR"
    },
    {
      "parameters": {
        "workflowId": {
          "__rl": true,
          "value": "yNJwTAF515h4EBLB",
          "mode": "list",
          "cachedResultUrl": "/workflow/yNJwTAF515h4EBLB",
          "cachedResultName": "KB-System — TransloaditOCR"
        },
        "workflowInputs": {
          "mappingMode": "defineBelow",
          "value": {},
          "matchingColumns": [],
          "schema": [],
          "attemptToConvertTypes": false,
          "convertFieldsToString": true
        },
        "options": {
          "waitForSubWorkflow": true
        }
      },
      "type": "n8n-nodes-base.executeWorkflow",
      "typeVersion": 1.3,
      "position": [
        448,
        576
      ],
      "id": "d9502d8a-f57d-4517-95e1-70ce3a46cdc6",
      "name": "Call 'TransloaditOCR'",
      "disabled": true
    },
    {
      "parameters": {
        "content": "\n\n\n\n\n\n\n\n\n\n\n\nStop Workflow on Error",
        "height": 192,
        "width": 192,
        "color": 7
      },
      "type": "n8n-nodes-base.stickyNote",
      "typeVersion": 1,
      "position": [
        176,
        0
      ],
      "id": "4f0a8968-0627-46c5-a5fd-9b45044f0fd4",
      "name": "Sticky Note4"
    },
    {
      "parameters": {
        "content": "\n\n\n\n\n\n\n\n\n\n\n\nStop Workflow on Error",
        "height": 192,
        "width": 192,
        "color": 7
      },
      "type": "n8n-nodes-base.stickyNote",
      "typeVersion": 1,
      "position": [
        400,
        192
      ],
      "id": "6eb71d0b-dc3a-4ba4-9efa-1882fdbd6d5a",
      "name": "Sticky Note"
    },
    {
      "parameters": {
        "content": "\n\n\n\n\n\n\n\n\n\n\nStop Workflow on Error",
        "width": 192,
        "color": 7
      },
      "type": "n8n-nodes-base.stickyNote",
      "typeVersion": 1,
      "position": [
        -496,
        1056
      ],
      "id": "04c4d19c-8743-4251-9705-29877d8ed5e3",
      "name": "Sticky Note5"
    },
    {
      "parameters": {
        "type": "SHA3-256",
        "value": "={{ $json.body }}",
        "dataPropertyName": "hash"
      },
      "type": "n8n-nodes-base.crypto",
      "typeVersion": 1,
      "position": [
        672,
        384
      ],
      "id": "ec9eb996-4b94-4ce2-b87a-5f55b351f970",
      "name": "HTML Hash"
    },
    {
      "parameters": {
        "type": "SHA3-256",
        "value": "={{ $json.cleanedMarkdown }}",
        "dataPropertyName": "hash"
      },
      "type": "n8n-nodes-base.crypto",
      "typeVersion": 1,
      "position": [
        1344,
        480
      ],
      "id": "a7db15b6-91f0-4991-b554-cdde823d32dd",
      "name": "Markdown Hash",
      "disabled": true
    },
    {
      "parameters": {
        "content": "\n\n\n\n\n\n\n\n\n\n\n\n\nHash Markdown Value instead of full HTML",
        "height": 208,
        "width": 192,
        "color": 7
      },
      "type": "n8n-nodes-base.stickyNote",
      "typeVersion": 1,
      "position": [
        1296,
        480
      ],
      "id": "495db092-4bf0-4501-97ef-9ecac9671f13",
      "name": "Sticky Note6"
    }
  ],
  "pinData": {},
  "connections": {
    "Browserless": {
      "main": [
        [
          {
            "node": "Set Source",
            "type": "main",
            "index": 0
          }
        ],
        [
          {
            "node": "Append Error (Browserless)",
            "type": "main",
            "index": 0
          }
        ]
      ]
    },
    "Type Switch": {
      "main": [
        [
          {
            "node": "HTTP Request",
            "type": "main",
            "index": 0
          }
        ],
        [
          {
            "node": "PDF Binary",
            "type": "main",
            "index": 0
          }
        ],
        [
          {
            "node": "Stop and Error",
            "type": "main",
            "index": 0
          }
        ]
      ]
    },
    "When Executed by Another Workflow": {
      "main": [
        [
          {
            "node": "Set Inputs",
            "type": "main",
            "index": 0
          }
        ]
      ]
    },
    "When clicking ‘Execute workflow’": {
      "main": [
        [
          {
            "node": "Manual",
            "type": "main",
            "index": 0
          }
        ]
      ]
    },
    "HTTP Request": {
      "main": [
        [
          {
            "node": "Browserless",
            "type": "main",
            "index": 0
          }
        ],
        [
          {
            "node": "Append Error (HTTP Request)",
            "type": "main",
            "index": 0
          }
        ]
      ]
    },
    "Set Source": {
      "main": [
        [
          {
            "node": "Set Upload",
            "type": "main",
            "index": 0
          }
        ]
      ]
    },
    "Manual": {
      "main": [
        [
          {
            "node": "Set Inputs",
            "type": "main",
            "index": 0
          }
        ]
      ]
    },
    "Set Inputs": {
      "main": [
        [
          {
            "node": "Type Switch",
            "type": "main",
            "index": 0
          }
        ]
      ]
    },
    "HTML Catch": {
      "main": [
        [
          {
            "node": "HTML Failover",
            "type": "main",
            "index": 0
          }
        ],
        [
          {
            "node": "Append Crawl-Output (PDF)",
            "type": "main",
            "index": 0
          },
          {
            "node": "Calculate File Size",
            "type": "main",
            "index": 0
          }
        ]
      ]
    },
    "HTML Failover": {
      "main": [
        [
          {
            "node": "HTTP Request",
            "type": "main",
            "index": 0
          }
        ]
      ]
    },
    "Append Crawl-Output (PDF)": {
      "main": [
        [
          {
            "node": "Set Workflow Output (PDF)",
            "type": "main",
            "index": 0
          }
        ]
      ]
    },
    "Append Error (HTTP Request)": {
      "main": [
        [
          {
            "node": "Stop and Error (HTTP Request)",
            "type": "main",
            "index": 0
          }
        ]
      ]
    },
    "Append Error (Browserless)": {
      "main": [
        [
          {
            "node": "Stop and Error (Browserless)",
            "type": "main",
            "index": 0
          }
        ]
      ]
    },
    "Append Error (PDF)": {
      "main": [
        [
          {
            "node": "Stop and Error (PDF)",
            "type": "main",
            "index": 0
          }
        ]
      ]
    },
    "PDF Binary": {
      "main": [
        [
          {
            "node": "HTML Catch",
            "type": "main",
            "index": 0
          }
        ],
        [
          {
            "node": "Append Error (PDF)",
            "type": "main",
            "index": 0
          }
        ]
      ]
    },
    "Merge PDF": {
      "main": [
        [
          {
            "node": "Final PDF",
            "type": "main",
            "index": 0
          }
        ]
      ]
    },
    "Upload Merge": {
      "main": [
        [
          {
            "node": "Update Unformatted-PDF",
            "type": "main",
            "index": 0
          },
          {
            "node": "Update Scrape-Output (PDF)",
            "type": "main",
            "index": 0
          }
        ]
      ]
    },
    "Set ID": {
      "main": [
        [
          {
            "node": "Upload Merge",
            "type": "main",
            "index": 1
          }
        ]
      ]
    },
    "Success": {
      "main": [
        [
          {
            "node": "Set ID",
            "type": "main",
            "index": 0
          }
        ]
      ]
    },
    "Upload-PDF": {
      "main": [
        [
          {
            "node": "Success",
            "type": "main",
            "index": 0
          }
        ]
      ]
    },
    "Upload-Formatted-PDF": {
      "main": [
        [
          {
            "node": "Update Formatted-PDF",
            "type": "main",
            "index": 0
          }
        ]
      ]
    },
    "Final PDF": {
      "main": [
        [
          {
            "node": "Upload-Formatted-PDF",
            "type": "main",
            "index": 0
          },
          {
            "node": "Upload Merge",
            "type": "main",
            "index": 0
          }
        ]
      ]
    },
    "Set PDF Data": {
      "main": [
        [
          {
            "node": "Merge PDF",
            "type": "main",
            "index": 1
          }
        ]
      ]
    },
    "Set PDF Hash": {
      "main": [
        [
          {
            "node": "Merge PDF",
            "type": "main",
            "index": 0
          }
        ]
      ]
    },
    "PDF Hash": {
      "main": [
        [
          {
            "node": "Set PDF Hash",
            "type": "main",
            "index": 0
          }
        ]
      ]
    },
    "Extract PDF Data": {
      "main": [
        [
          {
            "node": "Set PDF Data",
            "type": "main",
            "index": 0
          }
        ]
      ]
    },
    "Convert HTML to Markdown": {
      "main": [
        [
          {
            "node": "Clean Markdown",
            "type": "main",
            "index": 0
          }
        ]
      ]
    },
    "Upload-Formatted-HTML": {
      "main": [
        [
          {
            "node": "Update Scrape-Output (HTML)",
            "type": "main",
            "index": 0
          },
          {
            "node": "Update Formatted-HTML",
            "type": "main",
            "index": 0
          }
        ]
      ]
    },
    "Clean Markdown": {
      "main": [
        [
          {
            "node": "Markdown Hash",
            "type": "main",
            "index": 0
          }
        ]
      ]
    },
    "Upload-Unformatted-HTML": {
      "main": [
        [
          {
            "node": "Update Unformatted-HTML",
            "type": "main",
            "index": 0
          }
        ]
      ]
    },
    "Set Formatted HTML": {
      "main": [
        [
          {
            "node": "Upload-Formatted-HTML",
            "type": "main",
            "index": 0
          }
        ]
      ]
    },
    "Set Unformatted HTML": {
      "main": [
        [
          {
            "node": "Upload-Unformatted-HTML",
            "type": "main",
            "index": 0
          }
        ]
      ]
    },
    "Update Scrape-Output (PDF)": {
      "main": [
        [
          {
            "node": "Set Output (PDF Scrape)",
            "type": "main",
            "index": 0
          }
        ]
      ]
    },
    "Update Scrape-Output (HTML)": {
      "main": [
        [
          {
            "node": "Set Output (HTML Scrape)",
            "type": "main",
            "index": 0
          }
        ]
      ]
    },
    "Set Upload": {
      "main": [
        [
          {
            "node": "HTML Hash",
            "type": "main",
            "index": 0
          }
        ]
      ]
    },
    "Calculate File Size": {
      "main": [
        [
          {
            "node": "Greater Than 15mb",
            "type": "main",
            "index": 0
          }
        ]
      ]
    },
    "Append Error (PDF Size)": {
      "main": [
        [
          {
            "node": "Set TransloaditOCR",
            "type": "main",
            "index": 0
          }
        ]
      ]
    },
    "Greater Than 15mb": {
      "main": [
        [
          {
            "node": "Append Error (PDF Size)",
            "type": "main",
            "index": 0
          }
        ],
        [
          {
            "node": "PDF Hash",
            "type": "main",
            "index": 0
          },
          {
            "node": "Extract PDF Data",
            "type": "main",
            "index": 0
          },
          {
            "node": "Upload-PDF",
            "type": "main",
            "index": 0
          }
        ]
      ]
    },
    "Set TransloaditOCR": {
      "main": [
        [
          {
            "node": "Call 'TransloaditOCR'",
            "type": "main",
            "index": 0
          }
        ]
      ]
    },
    "Call 'TransloaditOCR'": {
      "main": [
        [
          {
            "node": "Set Workflow Output (PDF Error)2",
            "type": "main",
            "index": 0
          }
        ]
      ]
    },
    "HTML Hash": {
      "main": [
        [
          {
            "node": "Set Unformatted HTML",
            "type": "main",
            "index": 0
          },
          {
            "node": "Convert HTML to Markdown",
            "type": "main",
            "index": 0
          }
        ]
      ]
    },
    "Markdown Hash": {
      "main": [
        [
          {
            "node": "Set Formatted HTML",
            "type": "main",
            "index": 0
          }
        ]
      ]
    }
  },
  "active": false,
  "settings": {
    "executionOrder": "v1",
    "binaryMode": "separate",
    "availableInMCP": false
  },
  "versionId": "18fb3cb5-0770-4005-810f-3814e1e39c37",
  "meta": {
    "templateCredsSetupCompleted": true,
    "instanceId": "e90f7f7e6a26b85872ce66ded5d7910e921575d60b70d6a45b57c87eb5310c2c"
  },
  "id": "85qKnLvq0YcemyHI",
  "tags": []
}